cv2operator/__init__.py
cv2operator/brush_operator.py
cv2operator/key_operator.py
cv2operator/line_operator.py
cv2operator/mouse_operator.py
cv2operator/poly_operator.py
cv2operator/rect_operator.py
cv2operator/window.py
cv2operator-1.0.1.dist-info/LICENSE
cv2operator-1.0.1.dist-info/METADATA
cv2operator-1.0.1.dist-info/WHEEL
cv2operator-1.0.1.dist-info/top_level.txt
cv2operator-1.0.1.dist-info/RECORD
