Metadata-Version: 2.1
Name: cv2operator
Version: 1.0.1
Summary: a simple library to input various shapes like polygon rectangle and so on.
Home-page: https://github.com/moicci/cv2operator
Author: fukuda, minoru
License: MIT
Keywords: opencv cv2 operation
Platform: UNKNOWN
Classifier: License :: OSI Approved :: MIT License
Classifier: Programming Language :: Python :: 3.7
